finch/__init__.py
finch/__version__.py
finch/cli.py
finch/datasets.yml
finch/default.cfg
finch/wsgi.py
finch/processes/__init__.py
finch/processes/ensemble_utils.py
finch/processes/subset.py
finch/processes/utils.py
finch/processes/virtual.py
finch/processes/wps_base.py
finch/processes/wps_ensemble_indices_bbox.py
finch/processes/wps_ensemble_indices_point.py
finch/processes/wps_ensemble_indices_polygon.py
finch/processes/wps_geoseries_to_netcdf.py
finch/processes/wps_hourly_to_daily.py
finch/processes/wps_sdba.py
finch/processes/wps_xaverage_polygon.py
finch/processes/wps_xclim_indices.py
finch/processes/wps_xsubset_bbox.py
finch/processes/wps_xsubset_bbox_dataset.py
finch/processes/wps_xsubset_point.py
finch/processes/wps_xsubset_point_dataset.py
finch/processes/wps_xsubset_polygon.py
finch/processes/wpsio.py
finch/processes/modules/humidex.yml
finch/processes/modules/streamflow.yml
finch/templates/pywps.cfg
birdhouse_finch-0.13.2.dist-info/entry_points.txt
birdhouse_finch-0.13.2.dist-info/licenses/LICENSE
birdhouse_finch-0.13.2.dist-info/WHEEL
birdhouse_finch-0.13.2.dist-info/METADATA
birdhouse_finch-0.13.2.dist-info/RECORD
