Metadata-Version: 2.4
Name: birdhouse-finch
Version: 0.13.2
Summary: A Web Processing Service for Climate Indicators.
Keywords: wps,pywps,birdhouse,finch
Author-email: David Huard <huard.david@ouranos.ca>, Pascal Bourgault <bourgault.pascal@ouranos.ca>
Maintainer-email: Trevor James Smith <smith.trevorj@ouranos.ca>
Requires-Python: >=3.10.0
Classifier: Development Status :: 4 - Beta
Classifier: Intended Audience :: Developers
Classifier: Intended Audience :: Science/Research
Classifier: License :: OSI Approved :: Apache Software License
Classifier: Operating System :: MacOS :: MacOS X
Classifier: Operating System :: POSIX
Classifier: Programming Language :: Python
Classifier: Natural Language :: English
Classifier: Programming Language :: Python :: 3
Classifier: Programming Language :: Python :: 3.10
Classifier: Programming Language :: Python :: 3.11
Classifier: Programming Language :: Python :: 3.12
Classifier: Topic :: Scientific/Engineering :: Atmospheric Science
License-File: LICENSE
Requires-Dist: anyascii >=0.3.0
Requires-Dist: cf-xarray >=0.9.3
Requires-Dist: cftime >=1.4.1
Requires-Dist: click >=8.1.7
Requires-Dist: clisops >=0.16.2
Requires-Dist: dask[complete] >=2023.5.1,<2025.4.0
Requires-Dist: geopandas >=1.0
Requires-Dist: jinja2 >=3.1.4
Requires-Dist: netcdf4 <=1.7.2
Requires-Dist: numcodecs <0.16.0
Requires-Dist: numpy >=1.25.0
Requires-Dist: pandas >=2.2.0
Requires-Dist: parse
Requires-Dist: psutil >=6.0.0
Requires-Dist: python-slugify
Requires-Dist: pywps >=4.6.0
Requires-Dist: pyyaml >=6.0.1
Requires-Dist: scipy >=1.9.0
Requires-Dist: sentry-sdk
Requires-Dist: siphon
Requires-Dist: xarray >=2023.11.0,<2025.4.0
Requires-Dist: xclim ==0.52.2
Requires-Dist: xesmf >=0.6.2,!=0.8.8
Requires-Dist: xscen ==0.10.0
Requires-Dist: werkzeug>=3.0.6
Requires-Dist: birdhouse-birdy>=0.8.1 ; extra == "dev"
Requires-Dist: black >=24.10.0 ; extra == "dev"
Requires-Dist: bump-my-version >=0.29.0 ; extra == "dev"
Requires-Dist: coverage >=7.5.0 ; extra == "dev"
Requires-Dist: cruft >=2.15.0 ; extra == "dev"
Requires-Dist: flake8 >=7.1.0 ; extra == "dev"
Requires-Dist: flake8-rst-docstrings >=0.3.0 ; extra == "dev"
Requires-Dist: flit >=3.9.0,<4.0 ; extra == "dev"
Requires-Dist: geojson ; extra == "dev"
Requires-Dist: lxml ; extra == "dev"
Requires-Dist: matplotlib >=3.5.0 ; extra == "dev"
Requires-Dist: nbconvert ; extra == "dev"
Requires-Dist: nbsphinx>=0.9.5 ; extra == "dev"
Requires-Dist: nbval >=0.10.0 ; extra == "dev"
Requires-Dist: owslib ; extra == "dev"
Requires-Dist: pip >=24.2.0 ; extra == "dev"
Requires-Dist: pre-commit >=3.5.0 ; extra == "dev"
Requires-Dist: pylint >=3.3.3 ; extra == "dev"
Requires-Dist: pytest >=8.0.0 ; extra == "dev"
Requires-Dist: pytest-cov >=5.0.0 ; extra == "dev"
Requires-Dist: pytest-flake8 ; extra == "dev"
Requires-Dist: pytest-notebook ; extra == "dev"
Requires-Dist: ruff >=0.5.7 ; extra == "dev"
Requires-Dist: vulture >=2.14 ; extra == "dev"
Requires-Dist: watchdog >=4.0.0 ; extra == "dev"
Requires-Dist: birdhouse-birdy>=0.8.1 ; extra == "docs"
Requires-Dist: cf-xarray>=0.9.3 ; extra == "docs"
Requires-Dist: cftime>=1.4.1 ; extra == "docs"
Requires-Dist: ipython>=8.0.0 ; extra == "docs"
Requires-Dist: jupyter_client ; extra == "docs"
Requires-Dist: matplotlib>=3.5.0 ; extra == "docs"
Requires-Dist: nbsphinx>=0.9.5 ; extra == "docs"
Requires-Dist: sphinx>=7.0.0,<8.2.0 ; extra == "docs"
Requires-Dist: sphinxcontrib-bibtex>=2.6.0 ; extra == "docs"
Requires-Dist: gunicorn>=23.0.0 ; extra == "prod"
Requires-Dist: psycopg2-binary>=2.9.9 ; extra == "prod"
Project-URL: Changelog, https://github.com/bird-house/finch/blob/master/changelog.rst
Project-URL: Homepage, https://github.com/bird-house/finch
Project-URL: Issue tracker, https://github.com/bird-house/finch/issues
Provides-Extra: dev
Provides-Extra: docs
Provides-Extra: prod
